i2c_master.v
`default_nettype none

module I2C_MASTER(
    input  wire       CLK_IW,
    input  wire       RST_IW,
    input  wire       START_IW,
    input  wire [6:0] ADDR_IW,
    input  wire [7:0] DATA_IW,
    output wire       SCL_OW,
    output reg        SDA_OR,
    output wire       READY_OW
);

    reg [7:0] count;
    reg [7:0] state;
    reg [7:0] data;
    reg [6:0] address;
    reg       scl_enable = 0;

    assign SCL_OW   = (scl_enable == 0) ? 1 : ~CLK_IW;
    assign READY_OW = ((RST_IW == 0) && (state == ST_IDLE)) ? 1 : 0;


    always @(negedge CLK_IW) begin
        if(RST_IW) begin
            scl_enable <= 0;
        end else begin
            if((state == ST_IDLE) || (state == ST_START) || (state == ST_STOP)) begin
                scl_enable <= 0;
            end else begin
                scl_enable <= 1;
            end
        end
    end


    localparam ST_IDLE          = 0;
    localparam ST_START         = 1;
    localparam ST_ADDR          = 2;
    localparam ST_READ_WRITE    = 3;
    localparam ST_WAIT_ACK_ADDR = 4;
    localparam ST_DATA          = 5;
    localparam ST_WAIT_ACK_DATA = 6;
    localparam ST_STOP          = 7;

    always @(posedge CLK_IW) begin
        if(RST_IW) begin       
            SDA_OR  <= 1;
            count   <= 8'd0;
            state   <= ST_IDLE;
        end else begin
            case(state)
                ST_IDLE: begin
                    $display("state: %d", state);

                    SDA_OR <= 1;
                    if(START_IW) begin
                        data    <= DATA_IW;
                        address <= ADDR_IW;
                        state   <= ST_START;
                    end else begin
                        state <= ST_IDLE;
                    end 
                end // ST_IDLE

                ST_START: begin
                    $display("state: %d", state);

                    SDA_OR   <= 0;
                    state <= ST_ADDR;
                    count <= 6;
                end // ST_START

                ST_ADDR: begin
                    $display("state: %d, address[%d]: %d", state, count, address[count]);

                    SDA_OR <= address[count]; // MSBF
                    count <= count-1;           

                    if(count == 0) state <= ST_READ_WRITE;
                end // ST_ADDR

                ST_READ_WRITE: begin
                    $display("state: %d", state);

                    SDA_OR <= 1;   // 0 - read ; 1 - write
                    state  <= ST_WAIT_ACK_ADDR;
                end // ST_READ_WRITE

                ST_WAIT_ACK_ADDR: begin
                    $display("state: %d", state);

                    state <= ST_DATA;
                    count <= 7;
                end // ST_WAIT_ACK_ADDR

                ST_DATA: begin
                    $display("state: %d, data[%d]: %d", state, count, data[count]);

                    SDA_OR <= data[count];
                    count  <= count-1;

                    if(count == 0) state <= ST_WAIT_ACK_DATA;
                end // ST_DATA

                ST_WAIT_ACK_DATA: begin
                    $display("state: %d", state);

                    state <= ST_STOP;
                end // ST_WAIT_ACK_DATA

                ST_STOP: begin 
                    $display("state: %d", state);   
                    
                    SDA_OR <= 1;
                    state  <= ST_IDLE;
                end // ST_STOP
            endcase
        end
    end
endmodule

i2c_clk_divider.v
module CLK_DIVIDER(
    input  wire REF_CLK,
    input  wire RST,
    output reg  SCL
);

    parameter DELAY = 1000;
    reg [9:0] count = 0;
    initial   SCL   = 0;
    
    always @(REF_CLK) begin
        if(count == (DELAY/2)) begin
            SCL = ~SCL;
            count = 1000;
        end else begin
            count = count+1;
        end
    end

endmodule

i2c_master_tb.v
`timescale 1ns/1ps

`include "i2c_clk_divider.v"

module I2C_MASTER_TB();
    reg       clk;
    reg       rst;
    reg       start;
    reg [6:0] addr_in;
    reg [7:0] data_in;

    wire sda;
    wire scl;
    wire ready;

    wire i2c_clk;
    CLK_DIVIDER #(
        .DELAY(1000)
    ) divider(
        .REF_CLK(clk),
        .RST(rst),
        .SCL(i2c_clk)
    );

    I2C_MASTER uut(
        .CLK_IW(i2c_clk),
        .RST_IW(rst),
        .START_IW(start),
        .ADDR_IW(addr_in),
        .DATA_IW(data_in),
        .SCL_OW(SCL),
        .SDA_OR(SDA),
        .READY_OW(ready)
    );

    initial begin
        clk = 0;
        forever begin
            clk = #5 ~clk;
        end
    end

    initial begin
        $dumpfile("i2c_master.vcd");
        $dumpvars(0, I2C_MASTER_TB);

        start   = 1;
        addr_in = 7'b1011001;
        data_in = 8'b11001011;

        rst = 1;
        #10000;
        rst = 0;
        #112500;
        $finish;
    end
endmodule

i2c_master.vcd
$date
	Tue Oct 29 19:27:57 2024
$end
$version
	Icarus Verilog
$end
$timescale
	1ps
$end
$scope module I2C_MASTER_TB $end
$var wire 1 ! ready $end
$var wire 1 " i2c_clk $end
$var wire 1 # SDA $end
$var wire 1 $ SCL $end
$var reg 7 % addr_in [6:0] $end
$var reg 1 & clk $end
$var reg 8 ' data_in [7:0] $end
$var reg 1 ( rst $end
$var reg 1 ) start $end
$scope module divider $end
$var wire 1 & REF_CLK $end
$var wire 1 ( RST $end
$var parameter 32 * DELAY $end
$var reg 1 " SCL $end
$var reg 10 + count [9:0] $end
$upscope $end
$scope module uut $end
$var wire 7 , ADDR_IW [6:0] $end
$var wire 1 " CLK_IW $end
$var wire 8 - DATA_IW [7:0] $end
$var wire 1 ( RST_IW $end
$var wire 1 ) START_IW $end
$var wire 1 $ SCL_OW $end
$var wire 1 ! READY_OW $end
$var parameter 32 . ST_ADDR $end
$var parameter 32 / ST_DATA $end
$var parameter 32 0 ST_IDLE $end
$var parameter 32 1 ST_READ_WRITE $end
$var parameter 32 2 ST_START $end
$var parameter 32 3 ST_STOP $end
$var parameter 32 4 ST_WAIT_ACK_ADDR $end
$var parameter 32 5 ST_WAIT_ACK_DATA $end
$var reg 1 # SDA_OR $end
$var reg 7 6 address [6:0] $end
$var reg 8 7 count [7:0] $end
$var reg 8 8 data [7:0] $end
$var reg 1 9 scl_enable $end
$var reg 8 : state [7:0] $end
$upscope $end
$upscope $end
$enddefinitions $end
$comment Show the parameter values. $end
$dumpall
b110 5
b100 4
b111 3
b1 2
b11 1
b0 0
b101 /
b10 .
b1111101000 *
$end
#0
$dumpvars
bx :
09
bx 8
bx 7
bx 6
b11001011 -
b1011001 ,
b1 +
1)
1(
b11001011 '
0&
b1011001 %
1$
x#
0"
0!
$end
#5000
b10 +
1&
#10000
b11 +
0&
#15000
b100 +
1&
#20000
b101 +
0&
#25000
b110 +
1&
#30000
b111 +
0&
#35000
b1000 +
1&
#40000
b1001 +
0&
#45000
b1010 +
1&
#50000
b1011 +
0&
#55000
b1100 +
1&
#60000
b1101 +
0&
#65000
b1110 +
1&
#70000
b1111 +
0&
#75000
b10000 +
1&
#80000
b10001 +
0&
#85000
b10010 +
1&
#90000
b10011 +
0&
#95000
b10100 +
1&
#100000
b10101 +
0&
#105000
b10110 +
1&
#110000
b10111 +
0&
#115000
b11000 +
1&
#120000
b11001 +
0&
#125000
b11010 +
1&
#130000
b11011 +
0&
#135000
b11100 +
1&
#140000
b11101 +
0&
#145000
b11110 +
1&
#150000
b11111 +
0&
#155000
b100000 +
1&
#160000
b100001 +
0&
#165000
b100010 +
1&
#170000
b100011 +
0&
#175000
b100100 +
1&
#180000
b100101 +
0&
#185000
b100110 +
1&
#190000
b100111 +
0&
#195000
b101000 +
1&
#200000
b101001 +
0&
#205000
b101010 +
1&
#210000
b101011 +
0&
#215000
b101100 +
1&
#220000
b101101 +
0&
#225000
b101110 +
1&
#230000
b101111 +
0&
#235000
b110000 +
1&
#240000
b110001 +
0&
#245000
b110010 +
1&
#250000
b110011 +
0&
#255000
b110100 +
1&
#260000
b110101 +
0&
#265000
b110110 +
1&
#270000
b110111 +
0&
#275000
b111000 +
1&
#280000
b111001 +
0&
#285000
b111010 +
1&
#290000
b111011 +
0&
#295000
b111100 +
1&
#300000
b111101 +
0&
#305000
b111110 +
1&
#310000
b111111 +
0&
#315000
b1000000 +
1&
#320000
b1000001 +
0&
#325000
b1000010 +
1&
#330000
b1000011 +
0&
#335000
b1000100 +
1&
#340000
b1000101 +
0&
#345000
b1000110 +
1&
#350000
b1000111 +
0&
#355000
b1001000 +
1&
#360000
b1001001 +
0&
#365000
b1001010 +
1&
#370000
b1001011 +
0&
#375000
b1001100 +
1&
#380000
b1001101 +
0&
#385000
b1001110 +
1&
#390000
b1001111 +
0&
#395000
b1010000 +
1&
#400000
b1010001 +
0&
#405000
b1010010 +
1&
#410000
b1010011 +
0&
#415000
b1010100 +
1&
#420000
b1010101 +
0&
#425000
b1010110 +
1&
#430000
b1010111 +
0&
#435000
b1011000 +
1&
#440000
b1011001 +
0&
#445000
b1011010 +
1&
#450000
b1011011 +
0&
#455000
b1011100 +
1&
#460000
b1011101 +
0&
#465000
b1011110 +
1&
#470000
b1011111 +
0&
#475000
b1100000 +
1&
#480000
b1100001 +
0&
#485000
b1100010 +
1&
#490000
b1100011 +
0&
#495000
b1100100 +
1&
#500000
b1100101 +
0&
#505000
b1100110 +
1&
#510000
b1100111 +
0&
#515000
b1101000 +
1&
#520000
b1101001 +
0&
#525000
b1101010 +
1&
#530000
b1101011 +
0&
#535000
b1101100 +
1&
#540000
b1101101 +
0&
#545000
b1101110 +
1&
#550000
b1101111 +
0&
#555000
b1110000 +
1&
#560000
b1110001 +
0&
#565000
b1110010 +
1&
#570000
b1110011 +
0&
#575000
b1110100 +
1&
#580000
b1110101 +
0&
#585000
b1110110 +
1&
#590000
b1110111 +
0&
#595000
b1111000 +
1&
#600000
b1111001 +
0&
#605000
b1111010 +
1&
#610000
b1111011 +
0&
#615000
b1111100 +
1&
#620000
b1111101 +
0&
#625000
b1111110 +
1&
#630000
b1111111 +
0&
#635000
b10000000 +
1&
#640000
b10000001 +
0&
#645000
b10000010 +
1&
#650000
b10000011 +
0&
#655000
b10000100 +
1&
#660000
b10000101 +
0&
#665000
b10000110 +
1&
#670000
b10000111 +
0&
#675000
b10001000 +
1&
#680000
b10001001 +
0&
#685000
b10001010 +
1&
#690000
b10001011 +
0&
#695000
b10001100 +
1&
#700000
b10001101 +
0&
#705000
b10001110 +
1&
#710000
b10001111 +
0&
#715000
b10010000 +
1&
#720000
b10010001 +
0&
#725000
b10010010 +
1&
#730000
b10010011 +
0&
#735000
b10010100 +
1&
#740000
b10010101 +
0&
#745000
b10010110 +
1&
#750000
b10010111 +
0&
#755000
b10011000 +
1&
#760000
b10011001 +
0&
#765000
b10011010 +
1&
#770000
b10011011 +
0&
#775000
b10011100 +
1&
#780000
b10011101 +
0&
#785000
b10011110 +
1&
#790000
b10011111 +
0&
#795000
b10100000 +
1&
#800000
b10100001 +
0&
#805000
b10100010 +
1&
#810000
b10100011 +
0&
#815000
b10100100 +
1&
#820000
b10100101 +
0&
#825000
b10100110 +
1&
#830000
b10100111 +
0&
#835000
b10101000 +
1&
#840000
b10101001 +
0&
#845000
b10101010 +
1&
#850000
b10101011 +
0&
#855000
b10101100 +
1&
#860000
b10101101 +
0&
#865000
b10101110 +
1&
#870000
b10101111 +
0&
#875000
b10110000 +
1&
#880000
b10110001 +
0&
#885000
b10110010 +
1&
#890000
b10110011 +
0&
#895000
b10110100 +
1&
#900000
b10110101 +
0&
#905000
b10110110 +
1&
#910000
b10110111 +
0&
#915000
b10111000 +
1&
#920000
b10111001 +
0&
#925000
b10111010 +
1&
#930000
b10111011 +
0&
#935000
b10111100 +
1&
#940000
b10111101 +
0&
#945000
b10111110 +
1&
#950000
b10111111 +
0&
#955000
b11000000 +
1&
#960000
b11000001 +
0&
#965000
b11000010 +
1&
#970000
b11000011 +
0&
#975000
b11000100 +
1&
#980000
b11000101 +
0&
#985000
b11000110 +
1&
#990000
b11000111 +
0&
#995000
b11001000 +
1&
#1000000
b11001001 +
0&
#1005000
b11001010 +
1&
#1010000
b11001011 +
0&
#1015000
b11001100 +
1&
#1020000
b11001101 +
0&
#1025000
b11001110 +
1&
#1030000
b11001111 +
0&
#1035000
b11010000 +
1&
#1040000
b11010001 +
0&
#1045000
b11010010 +
1&
#1050000
b11010011 +
0&
#1055000
b11010100 +
1&
#1060000
b11010101 +
0&
#1065000
b11010110 +
1&
#1070000
b11010111 +
0&
#1075000
b11011000 +
1&
#1080000
b11011001 +
0&
#1085000
b11011010 +
1&
#1090000
b11011011 +
0&
#1095000
b11011100 +
1&
#1100000
b11011101 +
0&
#1105000
b11011110 +
1&
#1110000
b11011111 +
0&
#1115000
b11100000 +
1&
#1120000
b11100001 +
0&
#1125000
b11100010 +
1&
#1130000
b11100011 +
0&
#1135000
b11100100 +
1&
#1140000
b11100101 +
0&
#1145000
b11100110 +
1&
#1150000
b11100111 +
0&
#1155000
b11101000 +
1&
#1160000
b11101001 +
0&
#1165000
b11101010 +
1&
#1170000
b11101011 +
0&
#1175000
b11101100 +
1&
#1180000
b11101101 +
0&
#1185000
b11101110 +
1&
#1190000
b11101111 +
0&
#1195000
b11110000 +
1&
#1200000
b11110001 +
0&
#1205000
b11110010 +
1&
#1210000
b11110011 +
0&
#1215000
b11110100 +
1&
#1220000
b11110101 +
0&
#1225000
b11110110 +
1&
#1230000
b11110111 +
0&
#1235000
b11111000 +
1&
#1240000
b11111001 +
0&
#1245000
b11111010 +
1&
#1250000
b11111011 +
0&
#1255000
b11111100 +
1&
#1260000
b11111101 +
0&
#1265000
b11111110 +
1&
#1270000
b11111111 +
0&
#1275000
b100000000 +
1&
#1280000
b100000001 +
0&
#1285000
b100000010 +
1&
#1290000
b100000011 +
0&
#1295000
b100000100 +
1&
#1300000
b100000101 +
0&
#1305000
b100000110 +
1&
#1310000
b100000111 +
0&
#1315000
b100001000 +
1&
#1320000
b100001001 +
0&
#1325000
b100001010 +
1&
#1330000
b100001011 +
0&
#1335000
b100001100 +
1&
#1340000
b100001101 +
0&
#1345000
b100001110 +
1&
#1350000
b100001111 +
0&
#1355000
b100010000 +
1&
#1360000
b100010001 +
0&
#1365000
b100010010 +
1&
#1370000
b100010011 +
0&
#1375000
b100010100 +
1&
#1380000
b100010101 +
0&
#1385000
b100010110 +
1&
#1390000
b100010111 +
0&
#1395000
b100011000 +
1&
#1400000
b100011001 +
0&
#1405000
b100011010 +
1&
#1410000
b100011011 +
0&
#1415000
b100011100 +
1&
#1420000
b100011101 +
0&
#1425000
b100011110 +
1&
#1430000
b100011111 +
0&
#1435000
b100100000 +
1&
#1440000
b100100001 +
0&
#1445000
b100100010 +
1&
#1450000
b100100011 +
0&
#1455000
b100100100 +
1&
#1460000
b100100101 +
0&
#1465000
b100100110 +
1&
#1470000
b100100111 +
0&
#1475000
b100101000 +
1&
#1480000
b100101001 +
0&
#1485000
b100101010 +
1&
#1490000
b100101011 +
0&
#1495000
b100101100 +
1&
#1500000
b100101101 +
0&
#1505000
b100101110 +
1&
#1510000
b100101111 +
0&
#1515000
b100110000 +
1&
#1520000
b100110001 +
0&
#1525000
b100110010 +
1&
#1530000
b100110011 +
0&
#1535000
b100110100 +
1&
#1540000
b100110101 +
0&
#1545000
b100110110 +
1&
#1550000
b100110111 +
0&
#1555000
b100111000 +
1&
#1560000
b100111001 +
0&
#1565000
b100111010 +
1&
#1570000
b100111011 +
0&
#1575000
b100111100 +
1&
#1580000
b100111101 +
0&
#1585000
b100111110 +
1&
#1590000
b100111111 +
0&
#1595000
b101000000 +
1&
#1600000
b101000001 +
0&
#1605000
b101000010 +
1&
#1610000
b101000011 +
0&
#1615000
b101000100 +
1&
#1620000
b101000101 +
0&
#1625000
b101000110 +
1&
#1630000
b101000111 +
0&
#1635000
b101001000 +
1&
#1640000
b101001001 +
0&
#1645000
b101001010 +
1&
#1650000
b101001011 +
0&
#1655000
b101001100 +
1&
#1660000
b101001101 +
0&
#1665000
b101001110 +
1&
#1670000
b101001111 +
0&
#1675000
b101010000 +
1&
#1680000
b101010001 +
0&
#1685000
b101010010 +
1&
#1690000
b101010011 +
0&
#1695000
b101010100 +
1&
#1700000
b101010101 +
0&
#1705000
b101010110 +
1&
#1710000
b101010111 +
0&
#1715000
b101011000 +
1&
#1720000
b101011001 +
0&
#1725000
b101011010 +
1&
#1730000
b101011011 +
0&
#1735000
b101011100 +
1&
#1740000
b101011101 +
0&
#1745000
b101011110 +
1&
#1750000
b101011111 +
0&
#1755000
b101100000 +
1&
#1760000
b101100001 +
0&
#1765000
b101100010 +
1&
#1770000
b101100011 +
0&
#1775000
b101100100 +
1&
#1780000
b101100101 +
0&
#1785000
b101100110 +
1&
#1790000
b101100111 +
0&
#1795000
b101101000 +
1&
#1800000
b101101001 +
0&
#1805000
b101101010 +
1&
#1810000
b101101011 +
0&
#1815000
b101101100 +
1&
#1820000
b101101101 +
0&
#1825000
b101101110 +
1&
#1830000
b101101111 +
0&
#1835000
b101110000 +
1&
#1840000
b101110001 +
0&
#1845000
b101110010 +
1&
#1850000
b101110011 +
0&
#1855000
b101110100 +
1&
#1860000
b101110101 +
0&
#1865000
b101110110 +
1&
#1870000
b101110111 +
0&
#1875000
b101111000 +
1&
#1880000
b101111001 +
0&
#1885000
b101111010 +
1&
#1890000
b101111011 +
0&
#1895000
b101111100 +
1&
#1900000
b101111101 +
0&
#1905000
b101111110 +
1&
#1910000
b101111111 +
0&
#1915000
b110000000 +
1&
#1920000
b110000001 +
0&
#1925000
b110000010 +
1&
#1930000
b110000011 +
0&
#1935000
b110000100 +
1&
#1940000
b110000101 +
0&
#1945000
b110000110 +
1&
#1950000
b110000111 +
0&
#1955000
b110001000 +
1&
#1960000
b110001001 +
0&
#1965000
b110001010 +
1&
#1970000
b110001011 +
0&
#1975000
b110001100 +
1&
#1980000
b110001101 +
0&
#1985000
b110001110 +
1&
#1990000
b110001111 +
0&
#1995000
b110010000 +
1&
#2000000
b110010001 +
0&
#2005000
b110010010 +
1&
#2010000
b110010011 +
0&
#2015000
b110010100 +
1&
#2020000
b110010101 +
0&
#2025000
b110010110 +
1&
#2030000
b110010111 +
0&
#2035000
b110011000 +
1&
#2040000
b110011001 +
0&
#2045000
b110011010 +
1&
#2050000
b110011011 +
0&
#2055000
b110011100 +
1&
#2060000
b110011101 +
0&
#2065000
b110011110 +
1&
#2070000
b110011111 +
0&
#2075000
b110100000 +
1&
#2080000
b110100001 +
0&
#2085000
b110100010 +
1&
#2090000
b110100011 +
0&
#2095000
b110100100 +
1&
#2100000
b110100101 +
0&
#2105000
b110100110 +
1&
#2110000
b110100111 +
0&
#2115000
b110101000 +
1&
#2120000
b110101001 +
0&
#2125000
b110101010 +
1&
#2130000
b110101011 +
0&
#2135000
b110101100 +
1&
#2140000
b110101101 +
0&
#2145000
b110101110 +
1&
#2150000
b110101111 +
0&
#2155000
b110110000 +
1&
#2160000
b110110001 +
0&
#2165000
b110110010 +
1&
#2170000
b110110011 +
0&
#2175000
b110110100 +
1&
#2180000
b110110101 +
0&
#2185000
b110110110 +
1&
#2190000
b110110111 +
0&
#2195000
b110111000 +
1&
#2200000
b110111001 +
0&
#2205000
b110111010 +
1&
#2210000
b110111011 +
0&
#2215000
b110111100 +
1&
#2220000
b110111101 +
0&
#2225000
b110111110 +
1&
#2230000
b110111111 +
0&
#2235000
b111000000 +
1&
#2240000
b111000001 +
0&
#2245000
b111000010 +
1&
#2250000
b111000011 +
0&
#2255000
b111000100 +
1&
#2260000
b111000101 +
0&
#2265000
b111000110 +
1&
#2270000
b111000111 +
0&
#2275000
b111001000 +
1&
#2280000
b111001001 +
0&
#2285000
b111001010 +
1&
#2290000
b111001011 +
0&
#2295000
b111001100 +
1&
#2300000
b111001101 +
0&
#2305000
b111001110 +
1&
#2310000
b111001111 +
0&
#2315000
b111010000 +
1&
#2320000
b111010001 +
0&
#2325000
b111010010 +
1&
#2330000
b111010011 +
0&
#2335000
b111010100 +
1&
#2340000
b111010101 +
0&
#2345000
b111010110 +
1&
#2350000
b111010111 +
0&
#2355000
b111011000 +
1&
#2360000
b111011001 +
0&
#2365000
b111011010 +
1&
#2370000
b111011011 +
0&
#2375000
b111011100 +
1&
#2380000
b111011101 +
0&
#2385000
b111011110 +
1&
#2390000
b111011111 +
0&
#2395000
b111100000 +
1&
#2400000
b111100001 +
0&
#2405000
b111100010 +
1&
#2410000
b111100011 +
0&
#2415000
b111100100 +
1&
#2420000
b111100101 +
0&
#2425000
b111100110 +
1&
#2430000
b111100111 +
0&
#2435000
b111101000 +
1&
#2440000
b111101001 +
0&
#2445000
b111101010 +
1&
#2450000
b111101011 +
0&
#2455000
b111101100 +
1&
#2460000
b111101101 +
0&
#2465000
b111101110 +
1&
#2470000
b111101111 +
0&
#2475000
b111110000 +
1&
#2480000
b111110001 +
0&
#2485000
b111110010 +
1&
#2490000
b111110011 +
0&
#2495000
b111110100 +
1&
#2500000
b0 :
b0 7
1#
b1111101000 +
1"
0&
#2505000
b1111101001 +
1&
#2510000
b1111101010 +
0&
#2515000
b1111101011 +
1&
#2520000
b1111101100 +
0&
#2525000
b1111101101 +
1&
#2530000
b1111101110 +
0&
#2535000
b1111101111 +
1&
#2540000
b1111110000 +
0&
#2545000
b1111110001 +
1&
#2550000
b1111110010 +
0&
#2555000
b1111110011 +
1&
#2560000
b1111110100 +
0&
#2565000
b1111110101 +
1&
#2570000
b1111110110 +
0&
#2575000
b1111110111 +
1&
#2580000
b1111111000 +
0&
#2585000
b1111111001 +
1&
#2590000
b1111111010 +
0&
#2595000
b1111111011 +
1&
#2600000
b1111111100 +
0&
#2605000
b1111111101 +
1&
#2610000
b1111111110 +
0&
#2615000
b1111111111 +
1&
#2620000
b0 +
0&
#2625000
b1 +
1&
#2630000
b10 +
0&
#2635000
b11 +
1&
#2640000
b100 +
0&
#2645000
b101 +
1&
#2650000
b110 +
0&
#2655000
b111 +
1&
#2660000
b1000 +
0&
#2665000
b1001 +
1&
#2670000
b1010 +
0&
#2675000
b1011 +
1&
#2680000
b1100 +
0&
#2685000
b1101 +
1&
#2690000
b1110 +
0&
#2695000
b1111 +
1&
#2700000
b10000 +
0&
#2705000
b10001 +
1&
#2710000
b10010 +
0&
#2715000
b10011 +
1&
#2720000
b10100 +
0&
#2725000
b10101 +
1&
#2730000
b10110 +
0&
#2735000
b10111 +
1&
#2740000
b11000 +
0&
#2745000
b11001 +
1&
#2750000
b11010 +
0&
#2755000
b11011 +
1&
#2760000
b11100 +
0&
#2765000
b11101 +
1&
#2770000
b11110 +
0&
#2775000
b11111 +
1&
#2780000
b100000 +
0&
#2785000
b100001 +
1&
#2790000
b100010 +
0&
#2795000
b100011 +
1&
#2800000
b100100 +
0&
#2805000
b100101 +
1&
#2810000
b100110 +
0&
#2815000
b100111 +
1&
#2820000
b101000 +
0&
#2825000
b101001 +
1&
#2830000
b101010 +
0&
#2835000
b101011 +
1&
#2840000
b101100 +
0&
#2845000
b101101 +
1&
#2850000
b101110 +
0&
#2855000
b101111 +
1&
#2860000
b110000 +
0&
#2865000
b110001 +
1&
#2870000
b110010 +
0&
#2875000
b110011 +
1&
#2880000
b110100 +
0&
#2885000
b110101 +
1&
#2890000
b110110 +
0&
#2895000
b110111 +
1&
#2900000
b111000 +
0&
#2905000
b111001 +
1&
#2910000
b111010 +
0&
#2915000
b111011 +
1&
#2920000
b111100 +
0&
#2925000
b111101 +
1&
#2930000
b111110 +
0&
#2935000
b111111 +
1&
#2940000
b1000000 +
0&
#2945000
b1000001 +
1&
#2950000
b1000010 +
0&
#2955000
b1000011 +
1&
#2960000
b1000100 +
0&
#2965000
b1000101 +
1&
#2970000
b1000110 +
0&
#2975000
b1000111 +
1&
#2980000
b1001000 +
0&
#2985000
b1001001 +
1&
#2990000
b1001010 +
0&
#2995000
b1001011 +
1&
#3000000
b1001100 +
0&
#3005000
b1001101 +
1&
#3010000
b1001110 +
0&
#3015000
b1001111 +
1&
#3020000
b1010000 +
0&
#3025000
b1010001 +
1&
#3030000
b1010010 +
0&
#3035000
b1010011 +
1&
#3040000
b1010100 +
0&
#3045000
b1010101 +
1&
#3050000
b1010110 +
0&
#3055000
b1010111 +
1&
#3060000
b1011000 +
0&
#3065000
b1011001 +
1&
#3070000
b1011010 +
0&
#3075000
b1011011 +
1&
#3080000
b1011100 +
0&
#3085000
b1011101 +
1&
#3090000
b1011110 +
0&
#3095000
b1011111 +
1&
#3100000
b1100000 +
0&
#3105000
b1100001 +
1&
#3110000
b1100010 +
0&
#3115000
b1100011 +
1&
#3120000
b1100100 +
0&
#3125000
b1100101 +
1&
#3130000
b1100110 +
0&
#3135000
b1100111 +
1&
#3140000
b1101000 +
0&
#3145000
b1101001 +
1&
#3150000
b1101010 +
0&
#3155000
b1101011 +
1&
#3160000
b1101100 +
0&
#3165000
b1101101 +
1&
#3170000
b1101110 +
0&
#3175000
b1101111 +
1&
#3180000
b1110000 +
0&
#3185000
b1110001 +
1&
#3190000
b1110010 +
0&
#3195000
b1110011 +
1&
#3200000
b1110100 +
0&
#3205000
b1110101 +
1&
#3210000
b1110110 +
0&
#3215000
b1110111 +
1&
#3220000
b1111000 +
0&
#3225000
b1111001 +
1&
#3230000
b1111010 +
0&
#3235000
b1111011 +
1&
#3240000
b1111100 +
0&
#3245000
b1111101 +
1&
#3250000
b1111110 +
0&
#3255000
b1111111 +
1&
#3260000
b10000000 +
0&
#3265000
b10000001 +
1&
#3270000
b10000010 +
0&
#3275000
b10000011 +
1&
#3280000
b10000100 +
0&
#3285000
b10000101 +
1&
#3290000
b10000110 +
0&
#3295000
b10000111 +
1&
#3300000
b10001000 +
0&
#3305000
b10001001 +
1&
#3310000
b10001010 +
0&
#3315000
b10001011 +
1&
#3320000
b10001100 +
0&
#3325000
b10001101 +
1&
#3330000
b10001110 +
0&
#3335000
b10001111 +
1&
#3340000
b10010000 +
0&
#3345000
b10010001 +
1&
#3350000
b10010010 +
0&
#3355000
b10010011 +
1&
#3360000
b10010100 +
0&
#3365000
b10010101 +
1&
#3370000
b10010110 +
0&
#3375000
b10010111 +
1&
#3380000
b10011000 +
0&
#3385000
b10011001 +
1&
#3390000
b10011010 +
0&
#3395000
b10011011 +
1&
#3400000
b10011100 +
0&
#3405000
b10011101 +
1&
#3410000
b10011110 +
0&
#3415000
b10011111 +
1&
#3420000
b10100000 +
0&
#3425000
b10100001 +
1&
#3430000
b10100010 +
0&
#3435000
b10100011 +
1&
#3440000
b10100100 +
0&
#3445000
b10100101 +
1&
#3450000
b10100110 +
0&
#3455000
b10100111 +
1&
#3460000
b10101000 +
0&
#3465000
b10101001 +
1&
#3470000
b10101010 +
0&
#3475000
b10101011 +
1&
#3480000
b10101100 +
0&
#3485000
b10101101 +
1&
#3490000
b10101110 +
0&
#3495000
b10101111 +
1&
#3500000
b10110000 +
0&
#3505000
b10110001 +
1&
#3510000
b10110010 +
0&
#3515000
b10110011 +
1&
#3520000
b10110100 +
0&
#3525000
b10110101 +
1&
#3530000
b10110110 +
0&
#3535000
b10110111 +
1&
#3540000
b10111000 +
0&
#3545000
b10111001 +
1&
#3550000
b10111010 +
0&
#3555000
b10111011 +
1&
#3560000
b10111100 +
0&
#3565000
b10111101 +
1&
#3570000
b10111110 +
0&
#3575000
b10111111 +
1&
#3580000
b11000000 +
0&
#3585000
b11000001 +
1&
#3590000
b11000010 +
0&
#3595000
b11000011 +
1&
#3600000
b11000100 +
0&
#3605000
b11000101 +
1&
#3610000
b11000110 +
0&
#3615000
b11000111 +
1&
#3620000
b11001000 +
0&
#3625000
b11001001 +
1&
#3630000
b11001010 +
0&
#3635000
b11001011 +
1&
#3640000
b11001100 +
0&
#3645000
b11001101 +
1&
#3650000
b11001110 +
0&
#3655000
b11001111 +
1&
#3660000
b11010000 +
0&
#3665000
b11010001 +
1&
#3670000
b11010010 +
0&
#3675000
b11010011 +
1&
#3680000
b11010100 +
0&
#3685000
b11010101 +
1&
#3690000
b11010110 +
0&
#3695000
b11010111 +
1&
#3700000
b11011000 +
0&
#3705000
b11011001 +
1&
#3710000
b11011010 +
0&
#3715000
b11011011 +
1&
#3720000
b11011100 +
0&
#3725000
b11011101 +
1&
#3730000
b11011110 +
0&
#3735000
b11011111 +
1&
#3740000
b11100000 +
0&
#3745000
b11100001 +
1&
#3750000
b11100010 +
0&
#3755000
b11100011 +
1&
#3760000
b11100100 +
0&
#3765000
b11100101 +
1&
#3770000
b11100110 +
0&
#3775000
b11100111 +
1&
#3780000
b11101000 +
0&
#3785000
b11101001 +
1&
#3790000
b11101010 +
0&
#3795000
b11101011 +
1&
#3800000
b11101100 +
0&
#3805000
b11101101 +
1&
#3810000
b11101110 +
0&
#3815000
b11101111 +
1&
#3820000
b11110000 +
0&
#3825000
b11110001 +
1&
#3830000
b11110010 +
0&
#3835000
b11110011 +
1&
#3840000
b11110100 +
0&
#3845000
b11110101 +
1&
#3850000
b11110110 +
0&
#3855000
b11110111 +
1&
#3860000
b11111000 +
0&
#3865000
b11111001 +
1&
#3870000
b11111010 +
0&
#3875000
b11111011 +
1&
#3880000
b11111100 +
0&
#3885000
b11111101 +
1&
#3890000
b11111110 +
0&
#3895000
b11111111 +
1&
#3900000
b100000000 +
0&
#3905000
b100000001 +
1&
#3910000
b100000010 +
0&
#3915000
b100000011 +
1&
#3920000
b100000100 +
0&
#3925000
b100000101 +
1&
#3930000
b100000110 +
0&
#3935000
b100000111 +
1&
#3940000
b100001000 +
0&
#3945000
b100001001 +
1&
#3950000
b100001010 +
0&
#3955000
b100001011 +
1&
#3960000
b100001100 +
0&
#3965000
b100001101 +
1&
#3970000
b100001110 +
0&
#3975000
b100001111 +
1&
#3980000
b100010000 +
0&
#3985000
b100010001 +
1&
#3990000
b100010010 +
0&
#3995000
b100010011 +
1&
#4000000
b100010100 +
0&
#4005000
b100010101 +
1&
#4010000
b100010110 +
0&
#4015000
b100010111 +
1&
#4020000
b100011000 +
0&
#4025000
b100011001 +
1&
#4030000
b100011010 +
0&
#4035000
b100011011 +
1&
#4040000
b100011100 +
0&
#4045000
b100011101 +
1&
#4050000
b100011110 +
0&
#4055000
b100011111 +
1&
#4060000
b100100000 +
0&
#4065000
b100100001 +
1&
#4070000
b100100010 +
0&
#4075000
b100100011 +
1&
#4080000
b100100100 +
0&
#4085000
b100100101 +
1&
#4090000
b100100110 +
0&
#4095000
b100100111 +
1&
#4100000
b100101000 +
0&
#4105000
b100101001 +
1&
#4110000
b100101010 +
0&
#4115000
b100101011 +
1&
